huntlib/__init__.py
huntlib/data.py
huntlib/decorators.py
huntlib/domaintools.py
huntlib/elastic.py
huntlib/exceptions.py
huntlib/splunk.py
huntlib/util.py
huntlib-0.5.3.dist-info/LICENSE.txt
huntlib-0.5.3.dist-info/METADATA
huntlib-0.5.3.dist-info/WHEEL
huntlib-0.5.3.dist-info/top_level.txt
huntlib-0.5.3.dist-info/zip-safe
huntlib-0.5.3.dist-info/RECORD
