Metadata-Version: 2.1
Name: huntlib
Version: 0.5.3
Summary: A Python library to help with some common threat hunting data analysis operations
Home-page: https://github.com/target/huntlib
Author: David J. Bianco
Author-email: david.bianco@target.com
License: UNKNOWN
Platform: UNKNOWN
Classifier: Programming Language :: Python :: 3
Classifier: Programming Language :: Python :: 3.7
Classifier: Programming Language :: Python :: 3.8
Classifier: License :: OSI Approved :: MIT License
Requires-Dist: future
Requires-Dist: splunk-sdk
Requires-Dist: elasticsearch-dsl
Requires-Dist: pandas
Requires-Dist: numpy
Requires-Dist: jellyfish (>=0.8.2)
Requires-Dist: domaintools-api
Requires-Dist: tqdm
Requires-Dist: scipy
